stmpy/__init__.py
stmpy/client.py
stmpy/datastructures.py
stmpy/serialize.py
stmpy/sign.py
stmpy/simple.py
stmpy_lib/__init__.py
stmpy_lib/client.py
stmpy_lib/datastructures.py
stmpy_lib/serialize.py
stmpy_lib/sign.py
stmpy_lib/simple.py
stmpy_lib-0.1.0b0.dist-info/METADATA
stmpy_lib-0.1.0b0.dist-info/WHEEL
stmpy_lib-0.1.0b0.dist-info/top_level.txt
stmpy_lib-0.1.0b0.dist-info/zip-safe
stmpy_lib-0.1.0b0.dist-info/RECORD
